{
  "fullname": "Xinxin Yao",
  "lastname": "Yao",
  "currentrank": 421,
  "peakrank": 205,
  "peakfirst": 20250113,
  "peaklast": 20250120,
  "dob": 20031020,
  "ht": "",
  "hand": "L",
  "backhand": 2,
  "country": "CHN",
  "shortlist": 0,
  "careerjs": 0,
  "active": 1,
  "lastdate": 0,
  "twitter": "",
  "current_dubs": "\"UNR\"",
  "peak_dubs": "\"UNR\"",
  "peakfirst_dubs": "\"\"",
  "liverank": "",
  "chartagg": 0,
  "itf_id": "",
  "atp_id": "",
  "dc_id": 800512672,
  "wiki_id": "",
  "elo_rating": 1289,
  "elo_rank": 467,
  "slug": "XinxinYao",
  "tour": "WTA",
  "profile_url": "https://www.tennisabstract.com/cgi-bin/wplayer.cgi?p=XinxinYao",
  "jsfrag_url": "https://www.tennisabstract.com/jsfrags/XinxinYao.js",
  "page_title": "Tennis Abstract: Xinxin Yao Match Results, Splits, and Analysis"
}