{
  "fullname": "Jan Michael Gambill",
  "lastname": "Gambill",
  "currentrank": "",
  "peakrank": 14,
  "peakfirst": 20010618,
  "peaklast": 20010618,
  "dob": 19770603,
  "ht": 190,
  "hand": "R",
  "backhand": 2,
  "country": "USA",
  "shortlist": 0,
  "careerjs": 0,
  "active": 0,
  "lastdate": 20100927,
  "twitter": "",
  "current_dubs": "",
  "peak_dubs": 23,
  "peakfirst_dubs": 20021104,
  "liverank": "",
  "chartagg": 0,
  "itf_id": 10011637,
  "atp_id": "jan-michael-gambill/g352",
  "dc_id": 800188657,
  "wiki_id": "Jan-Michael_Gambill",
  "elo_rating": "",
  "elo_rank": "",
  "slug": "JanMichaelGambill",
  "tour": "ATP",
  "profile_url": "https://www.tennisabstract.com/cgi-bin/player.cgi?p=JanMichaelGambill",
  "jsfrag_url": "https://www.tennisabstract.com/jsfrags/JanMichaelGambill.js",
  "page_title": "Tennis Abstract: Jan Michael Gambill Match Results, Splits, and Analysis"
}