{
  "fullname": "Fernando Verdasco",
  "lastname": "Verdasco",
  "currentrank": "\"\"",
  "peakrank": 7,
  "peakfirst": 20090420,
  "peaklast": 20101101,
  "dob": 19831115,
  "ht": 188,
  "hand": "L",
  "backhand": 2,
  "country": "ESP",
  "shortlist": 0,
  "careerjs": 0,
  "active": 0,
  "lastdate": 20230904,
  "twitter": "FerVerdasco",
  "current_dubs": "\"UNR\"",
  "peak_dubs": "\"UNR\"",
  "peakfirst_dubs": "\"\"",
  "liverank": "",
  "chartagg": 0,
  "itf_id": 10021778,
  "atp_id": "V306",
  "dc_id": 800210111,
  "wiki_id": "Fernando_Verdasco",
  "elo_rating": "",
  "elo_rank": "",
  "slug": "FernandoVerdasco",
  "tour": "ATP",
  "profile_url": "https://www.tennisabstract.com/cgi-bin/player.cgi?p=FernandoVerdasco",
  "jsfrag_url": "https://www.tennisabstract.com/jsfrags/FernandoVerdasco.js",
  "page_title": "Tennis Abstract: Fernando Verdasco Match Results, Splits, and Analysis"
}