{
  "fullname": "Anne Kremer",
  "lastname": "Kremer",
  "currentrank": "",
  "peakrank": 18,
  "peakfirst": 20020729,
  "peaklast": 20020729,
  "dob": 19751017,
  "ht": "",
  "hand": "R",
  "backhand": 2,
  "country": "LUX",
  "shortlist": 0,
  "careerjs": 0,
  "active": 0,
  "lastdate": 20140209,
  "twitter": "",
  "current_dubs": "UNR",
  "peak_dubs": "UNR",
  "peakfirst_dubs": "",
  "liverank": "",
  "chartagg": 0,
  "itf_id": 20002886,
  "atp_id": "4152/title/anne-kremer",
  "dc_id": 800182276,
  "wiki_id": "Anne_Kremer",
  "elo_rating": "",
  "elo_rank": "",
  "slug": "AnneKremer",
  "tour": "WTA",
  "profile_url": "https://www.tennisabstract.com/cgi-bin/wplayer.cgi?p=AnneKremer",
  "jsfrag_url": "https://www.tennisabstract.com/jsfrags/AnneKremer.js",
  "page_title": "Tennis Abstract: Anne Kremer Match Results, Splits, and Analysis"
}