{
  "fullname": "Sara Bejlek",
  "lastname": "Bejlek",
  "currentrank": 40,
  "peakrank": 37,
  "peakfirst": 20260223,
  "peaklast": 20260223,
  "dob": 20060131,
  "ht": "",
  "hand": "L",
  "backhand": 2,
  "country": "CZE",
  "shortlist": 0,
  "careerjs": 0,
  "active": 1,
  "lastdate": 0,
  "twitter": "",
  "current_dubs": "\"UNR\"",
  "peak_dubs": "\"UNR\"",
  "peakfirst_dubs": "\"\"",
  "liverank": "",
  "chartagg": 0,
  "itf_id": "",
  "atp_id": "",
  "dc_id": "",
  "wiki_id": "",
  "elo_rating": 1842,
  "elo_rank": 38,
  "slug": "SaraBejlek",
  "tour": "WTA",
  "profile_url": "https://www.tennisabstract.com/cgi-bin/wplayer.cgi?p=SaraBejlek",
  "jsfrag_url": "https://www.tennisabstract.com/jsfrags/SaraBejlek.js",
  "page_title": "Tennis Abstract: Sara Bejlek Match Results, Splits, and Analysis"
}