{
  "fullname": "Katie Swan",
  "lastname": "Swan",
  "currentrank": 264,
  "peakrank": 118,
  "peakfirst": 20221010,
  "peaklast": 20221010,
  "dob": 19990324,
  "ht": 170,
  "hand": "R",
  "backhand": 2,
  "country": "GBR",
  "shortlist": 0,
  "careerjs": 0,
  "active": 1,
  "lastdate": 0,
  "twitter": "",
  "current_dubs": "\"UNR\"",
  "peak_dubs": "\"UNR\"",
  "peakfirst_dubs": "\"\"",
  "liverank": "",
  "chartagg": 0,
  "itf_id": 100168587,
  "atp_id": "24565/title/katie-swan",
  "dc_id": 800332433,
  "wiki_id": "Katie_Swan",
  "elo_rating": 1477,
  "elo_rank": 275,
  "slug": "KatieSwan",
  "tour": "WTA",
  "profile_url": "https://www.tennisabstract.com/cgi-bin/wplayer.cgi?p=KatieSwan",
  "jsfrag_url": "https://www.tennisabstract.com/jsfrags/KatieSwan.js",
  "page_title": "Tennis Abstract: Katie Swan Match Results, Splits, and Analysis"
}