{
  "fullname": "Philipp Kohlschreiber",
  "lastname": "Kohlschreiber",
  "currentrank": "\"\"",
  "peakrank": 16,
  "peakfirst": 20120730,
  "peaklast": 20120730,
  "dob": 19831016,
  "ht": 178,
  "hand": "R",
  "backhand": 1,
  "country": "GER",
  "shortlist": 0,
  "careerjs": 0,
  "active": 0,
  "lastdate": 20220627,
  "twitter": "KohliATP",
  "current_dubs": "\"UNR\"",
  "peak_dubs": "\"UNR\"",
  "peakfirst_dubs": "\"\"",
  "liverank": "",
  "chartagg": 0,
  "itf_id": 100000009,
  "atp_id": "K435",
  "dc_id": 800211560,
  "wiki_id": "Philipp_Kohlschreiber",
  "elo_rating": "",
  "elo_rank": "",
  "slug": "PhilippKohlschreiber",
  "tour": "ATP",
  "profile_url": "https://www.tennisabstract.com/cgi-bin/player.cgi?p=PhilippKohlschreiber",
  "jsfrag_url": "https://www.tennisabstract.com/jsfrags/PhilippKohlschreiber.js",
  "page_title": "Tennis Abstract: Philipp Kohlschreiber Match Results, Splits, and Analysis"
}