{
  "fullname": "Elena Gabriela Ruse",
  "lastname": "Ruse",
  "currentrank": 83,
  "peakrank": 51,
  "peakfirst": 20220523,
  "peaklast": 20220523,
  "dob": 19971106,
  "ht": "",
  "hand": "R",
  "backhand": 2,
  "country": "ROU",
  "shortlist": 0,
  "careerjs": 0,
  "active": 1,
  "lastdate": 0,
  "twitter": "",
  "current_dubs": "\"UNR\"",
  "peak_dubs": "\"UNR\"",
  "peakfirst_dubs": "\"\"",
  "liverank": "",
  "chartagg": 0,
  "itf_id": 100186560,
  "atp_id": "21024/title/elena-gabriela-ruse",
  "dc_id": "",
  "wiki_id": "",
  "elo_rating": 1763,
  "elo_rank": 82,
  "slug": "ElenaGabrielaRuse",
  "tour": "WTA",
  "profile_url": "https://www.tennisabstract.com/cgi-bin/wplayer.cgi?p=ElenaGabrielaRuse",
  "jsfrag_url": "https://www.tennisabstract.com/jsfrags/ElenaGabrielaRuse.js",
  "page_title": "Tennis Abstract: Elena Gabriela Ruse Match Results, Splits, and Analysis"
}