{
  "fullname": "Virginia Ruano Pascual",
  "lastname": "Ruano Pascual",
  "currentrank": "\"\"",
  "peakrank": 28,
  "peakfirst": 19990412,
  "peaklast": 19990419,
  "dob": 19730921,
  "ht": 169,
  "hand": "R",
  "backhand": 1,
  "country": "ESP",
  "shortlist": 0,
  "careerjs": 0,
  "active": 0,
  "lastdate": 20100510,
  "twitter": "",
  "current_dubs": "\"UNR\"",
  "peak_dubs": "\"UNR\"",
  "peakfirst_dubs": "\"\"",
  "liverank": "",
  "chartagg": 0,
  "itf_id": 20001383,
  "atp_id": "6855/title/virginia-ruano-pascual",
  "dc_id": 800181073,
  "wiki_id": "Virginia_Ruano_Pascual",
  "elo_rating": "",
  "elo_rank": "",
  "slug": "VirginiaRuanoPascual",
  "tour": "WTA",
  "profile_url": "https://www.tennisabstract.com/cgi-bin/wplayer.cgi?p=VirginiaRuanoPascual",
  "jsfrag_url": "https://www.tennisabstract.com/jsfrags/VirginiaRuanoPascual.js",
  "page_title": "Tennis Abstract: Virginia Ruano Pascual Match Results, Splits, and Analysis"
}