{
  "fullname": "Austin Krajicek",
  "lastname": "Krajicek",
  "currentrank": "\"\"",
  "peakrank": 94,
  "peakfirst": 20151026,
  "peaklast": 20151026,
  "dob": 19900616,
  "ht": 188,
  "hand": "L",
  "backhand": 2,
  "country": "USA",
  "shortlist": 0,
  "careerjs": 0,
  "active": 0,
  "lastdate": 20180730,
  "twitter": "AustinKrajicek",
  "current_dubs": "\"UNR\"",
  "peak_dubs": "\"UNR\"",
  "peakfirst_dubs": "\"\"",
  "liverank": "",
  "chartagg": 0,
  "itf_id": 100089443,
  "atp_id": "KA00",
  "dc_id": "",
  "wiki_id": "Austin_Krajicek",
  "elo_rating": "",
  "elo_rank": "",
  "slug": "AustinKrajicek",
  "tour": "ATP",
  "profile_url": "https://www.tennisabstract.com/cgi-bin/player.cgi?p=AustinKrajicek",
  "jsfrag_url": "https://www.tennisabstract.com/jsfrags/AustinKrajicek.js",
  "page_title": "Tennis Abstract: Austin Krajicek Match Results, Splits, and Analysis"
}