{
  "fullname": "Aryna Sabalenka",
  "lastname": "Sabalenka",
  "currentrank": 1,
  "peakrank": 1,
  "peakfirst": 20230911,
  "peaklast": 20260330,
  "dob": 19980505,
  "ht": 182,
  "hand": "R",
  "backhand": 2,
  "country": "BLR",
  "shortlist": 0,
  "careerjs": 0,
  "active": 1,
  "lastdate": 0,
  "twitter": "SabalenkaA",
  "current_dubs": "\"UNR\"",
  "peak_dubs": "\"UNR\"",
  "peakfirst_dubs": "\"\"",
  "liverank": "",
  "chartagg": 0,
  "itf_id": 100178970,
  "atp_id": "21548/title/aryna-sabalenka",
  "dc_id": 800342816,
  "wiki_id": "Aryna_Sabalenka",
  "elo_rating": 2266,
  "elo_rank": 1,
  "slug": "ArynaSabalenka",
  "tour": "WTA",
  "profile_url": "https://www.tennisabstract.com/cgi-bin/wplayer.cgi?p=ArynaSabalenka",
  "jsfrag_url": "https://www.tennisabstract.com/jsfrags/ArynaSabalenka.js",
  "page_title": "Tennis Abstract: Aryna Sabalenka Match Results, Splits, and Analysis"
}