{
  "fullname": "Mary Joe Fernandez",
  "lastname": "Fernandez",
  "currentrank": "",
  "peakrank": 4,
  "peakfirst": 19901022,
  "peaklast": 19910121,
  "dob": 19710819,
  "ht": 175,
  "hand": "R",
  "backhand": 2,
  "country": "USA",
  "shortlist": 0,
  "careerjs": 0,
  "active": 0,
  "lastdate": 20001014,
  "twitter": "",
  "current_dubs": "UNR",
  "peak_dubs": "UNR",
  "peakfirst_dubs": "",
  "liverank": "",
  "chartagg": 0,
  "itf_id": 20003072,
  "atp_id": "2349/title/mary-joe-fernandez",
  "dc_id": 800178703,
  "wiki_id": "Mary_Joe_Fernandez",
  "elo_rating": "",
  "elo_rank": "",
  "slug": "MaryJoeFernandez",
  "tour": "WTA",
  "profile_url": "https://www.tennisabstract.com/cgi-bin/wplayer.cgi?p=MaryJoeFernandez",
  "jsfrag_url": "https://www.tennisabstract.com/jsfrags/MaryJoeFernandez.js",
  "page_title": "Tennis Abstract: Mary Joe Fernandez Match Results, Splits, and Analysis"
}