{
  "fullname": "Filip Misolic",
  "lastname": "Misolic",
  "currentrank": 86,
  "peakrank": 76,
  "peakfirst": 20260209,
  "peaklast": 20260209,
  "dob": 20010808,
  "ht": 180,
  "hand": "R",
  "backhand": 2,
  "country": "AUT",
  "shortlist": 0,
  "careerjs": 0,
  "active": 1,
  "lastdate": 0,
  "twitter": "",
  "current_dubs": "\"UNR\"",
  "peak_dubs": "\"UNR\"",
  "peakfirst_dubs": "\"\"",
  "liverank": "",
  "chartagg": 0,
  "itf_id": 100228554,
  "atp_id": "M0JZ",
  "dc_id": "",
  "wiki_id": "",
  "elo_rating": 1587,
  "elo_rank": 191,
  "slug": "FilipMisolic",
  "tour": "ATP",
  "profile_url": "https://www.tennisabstract.com/cgi-bin/player.cgi?p=FilipMisolic",
  "jsfrag_url": "https://www.tennisabstract.com/jsfrags/FilipMisolic.js",
  "page_title": "Tennis Abstract: Filip Misolic Match Results, Splits, and Analysis"
}