{
  "fullname": "Melanie Klaffner",
  "lastname": "Klaffner",
  "currentrank": 1296,
  "peakrank": 175,
  "peakfirst": 20140127,
  "peaklast": 20140224,
  "dob": 19900522,
  "ht": 171,
  "hand": "R",
  "backhand": 2,
  "country": "AUT",
  "shortlist": 0,
  "careerjs": 0,
  "active": 1,
  "lastdate": 0,
  "twitter": "",
  "current_dubs": "UNR",
  "peak_dubs": "UNR",
  "peakfirst_dubs": "",
  "liverank": 667,
  "chartagg": 0,
  "itf_id": 100048743,
  "atp_id": "12052/title/melanie-klaffner",
  "dc_id": 800252544,
  "wiki_id": "",
  "elo_rating": "",
  "elo_rank": "",
  "slug": "MelanieKlaffner",
  "tour": "WTA",
  "profile_url": "https://www.tennisabstract.com/cgi-bin/wplayer.cgi?p=MelanieKlaffner",
  "jsfrag_url": "https://www.tennisabstract.com/jsfrags/MelanieKlaffner.js",
  "page_title": "Tennis Abstract: Melanie Klaffner Match Results, Splits, and Analysis"
}