{
  "fullname": "Rebecca Sramkova",
  "lastname": "Sramkova",
  "currentrank": 122,
  "peakrank": 33,
  "peakfirst": 20250714,
  "peaklast": 20250714,
  "dob": 19961019,
  "ht": "",
  "hand": "R",
  "backhand": 2,
  "country": "SVK",
  "shortlist": 0,
  "careerjs": 0,
  "active": 1,
  "lastdate": 0,
  "twitter": "",
  "current_dubs": "\"UNR\"",
  "peak_dubs": "\"UNR\"",
  "peakfirst_dubs": "\"\"",
  "liverank": "",
  "chartagg": 0,
  "itf_id": 100167673,
  "atp_id": "20852/title/rebecca-sramkova",
  "dc_id": "",
  "wiki_id": "",
  "elo_rating": 1707,
  "elo_rank": 109,
  "slug": "RebeccaSramkova",
  "tour": "WTA",
  "profile_url": "https://www.tennisabstract.com/cgi-bin/wplayer.cgi?p=RebeccaSramkova",
  "jsfrag_url": "https://www.tennisabstract.com/jsfrags/RebeccaSramkova.js",
  "page_title": "Tennis Abstract: Rebecca Sramkova Match Results, Splits, and Analysis"
}