{
  "fullname": "Zdenek Kolar",
  "lastname": "Kolar",
  "currentrank": 183,
  "peakrank": 111,
  "peakfirst": 20220613,
  "peaklast": 20220613,
  "dob": 19961009,
  "ht": 183,
  "hand": "R",
  "backhand": 2,
  "country": "CZE",
  "shortlist": 0,
  "careerjs": 0,
  "active": 1,
  "lastdate": 0,
  "twitter": "",
  "current_dubs": "\"UNR\"",
  "peak_dubs": "\"UNR\"",
  "peakfirst_dubs": "\"\"",
  "liverank": "",
  "chartagg": 0,
  "itf_id": 100167668,
  "atp_id": "KH56",
  "dc_id": "",
  "wiki_id": "Zden%C4%9Bk_Kol%C3%A1%C5%99",
  "elo_rating": 1513,
  "elo_rank": 256,
  "slug": "ZdenekKolar",
  "tour": "ATP",
  "profile_url": "https://www.tennisabstract.com/cgi-bin/player.cgi?p=ZdenekKolar",
  "jsfrag_url": "https://www.tennisabstract.com/jsfrags/ZdenekKolar.js",
  "page_title": "Tennis Abstract: Zdenek Kolar Match Results, Splits, and Analysis"
}