{
  "fullname": "Radek Stepanek",
  "lastname": "Stepanek",
  "currentrank": "\"\"",
  "peakrank": 8,
  "peakfirst": 20060710,
  "peaklast": 20060814,
  "dob": 19781127,
  "ht": 185,
  "hand": "R",
  "backhand": 2,
  "country": "CZE",
  "shortlist": 0,
  "careerjs": 0,
  "active": 0,
  "lastdate": 20170116,
  "twitter": "",
  "current_dubs": "\"UNR\"",
  "peak_dubs": "\"UNR\"",
  "peakfirst_dubs": "\"\"",
  "liverank": "",
  "chartagg": 0,
  "itf_id": 10010914,
  "atp_id": "S694",
  "dc_id": 800184949,
  "wiki_id": "Radek_Stepanek",
  "elo_rating": "",
  "elo_rank": "",
  "slug": "RadekStepanek",
  "tour": "ATP",
  "profile_url": "https://www.tennisabstract.com/cgi-bin/player.cgi?p=RadekStepanek",
  "jsfrag_url": "https://www.tennisabstract.com/jsfrags/RadekStepanek.js",
  "page_title": "Tennis Abstract: Radek Stepanek Match Results, Splits, and Analysis"
}